{"name":"build-javascript","namedChunkGroups":{"polyfill":{"name":"polyfill","assets":[{"name":"webpack-runtime-c84583db97d92ce6ba08.js","size":3147},{"name":"polyfill-0958bdedbad9479e7532.js","size":85876}],"filteredAssets":0,"assetsSize":89023,"filteredAuxiliaryAssets":2,"auxiliaryAssetsSize":221229},"app":{"name":"app","assets":[{"name":"webpack-runtime-c84583db97d92ce6ba08.js","size":3147},{"name":"framework-79604fecf3fd5d26b8d6.js","size":140580},{"name":"app-3e2c3fd32ed7c86b7acf.js","size":103508}],"filteredAssets":0,"assetsSize":247235,"filteredAuxiliaryAssets":3,"auxiliaryAssetsSize":744465},"component---src-pages-index-tsx":{"name":"component---src-pages-index-tsx","assets":[{"name":"component---src-pages-index-tsx-10b71a7d3581151f0e27.js","size":4767}],"filteredAssets":0,"assetsSize":4767,"filteredAuxiliaryAssets":1,"auxiliaryAssetsSize":8348}},"assetsByChunkName":{"polyfill":["webpack-runtime-c84583db97d92ce6ba08.js","polyfill-0958bdedbad9479e7532.js"],"app":["webpack-runtime-c84583db97d92ce6ba08.js","framework-79604fecf3fd5d26b8d6.js","app-3e2c3fd32ed7c86b7acf.js"],"component---src-pages-index-tsx":["component---src-pages-index-tsx-10b71a7d3581151f0e27.js"]},"childAssetsByChunkName":{}}